rainbow/__init__.py
rainbow/__main__.py
rainbow/ansi.py
rainbow/build.py
rainbow/cli.py
rainbow/filter.py
rainbow/transformer.py
rainbow/command/__init__.py
rainbow/command/execute.py
rainbow/command/noop.py
rainbow/command/print_config_names.py
rainbow/command/print_path.py
rainbow/command/stdin.py
rainbow/config/__init__.py
rainbow/config/loader.py
rainbow/config/locator.py
rainbow/config/parser.py
rainbow/config/builtin/df.cfg
rainbow/config/builtin/diff.cfg
rainbow/config/builtin/env.cfg
rainbow/config/builtin/host.cfg
rainbow/config/builtin/ifconfig.cfg
rainbow/config/builtin/java-stack-trace.cfg
rainbow/config/builtin/jboss.cfg
rainbow/config/builtin/md5sum.cfg
rainbow/config/builtin/mvn.cfg
rainbow/config/builtin/ping.cfg
rainbow/config/builtin/tcpdump.cfg
rainbow/config/builtin/tomcat.cfg
rainbow/config/builtin/traceroute.cfg
rainbow-2.8.0.data/scripts/rainbow
rainbow-2.8.0.dist-info/COPYING
rainbow-2.8.0.dist-info/METADATA
rainbow-2.8.0.dist-info/WHEEL
rainbow-2.8.0.dist-info/top_level.txt
rainbow-2.8.0.dist-info/RECORD
