Metadata-Version: 2.1
Name: rainbow
Version: 2.8.0
Summary: Colorize commands output using patterns.
Home-page: https://github.com/nicoulaj/rainbow
Author: Julien Nicoulaud
Author-email: julien.nicoulaud@gmail.com
License: GPLv3
Keywords: color colorize colorizer pattern
Platform: UNKNOWN
Classifier: Development Status :: 5 - Production/Stable
Classifier: Environment :: Console
Classifier: Operating System :: MacOS :: MacOS X
Classifier: Operating System :: POSIX
Classifier: Topic :: System
Classifier: Topic :: Utilities
Classifier: Intended Audience :: Developers
Classifier: Intended Audience :: End Users/Desktop
Classifier: Intended Audience :: System Administrators
Classifier: Natural Language :: English
Classifier: Programming Language :: Python
Classifier: Programming Language :: Python :: 3
Classifier: Programming Language :: Python :: 3.6
Classifier: Programming Language :: Python :: 3.7
Classifier: Programming Language :: Python :: 3.8
Classifier: Programming Language :: Python :: 3.9
Classifier: Programming Language :: Python :: 3.10
Classifier: Programming Language :: Python :: Implementation :: CPython
Classifier: Programming Language :: Python :: Implementation :: PyPy
Classifier: License :: OSI Approved :: GNU General Public License (GPL)
Requires-Python: >=3.6
License-File: COPYING
Provides-Extra: build
Requires-Dist: Jinja2 (==3.0.3) ; extra == 'build'
Provides-Extra: test
Requires-Dist: pytest (==6.2.5) ; extra == 'test'
Requires-Dist: coverage (==6.2) ; extra == 'test'
Requires-Dist: pytest-cov (==3.0.0) ; extra == 'test'
Requires-Dist: pytest-html (==3.1.1) ; extra == 'test'
Requires-Dist: pytest-timeout (==2.0.2) ; extra == 'test'
Requires-Dist: flake8 (==4.0.1) ; extra == 'test'
Requires-Dist: pygal (==3.0.0) ; extra == 'test'
Requires-Dist: pygaljs (==1.0.2) ; extra == 'test'
Requires-Dist: pytest-benchmark (==3.4.1) ; extra == 'test'
